shapes/Equilateral_Triangle.py
shapes/Right_Angled_Triangle.py
shapes/__init__.py
shapes/butterfly.py
shapes/kite.py
pygeoshapes-1.0.dist-info/LICENSE.txt
pygeoshapes-1.0.dist-info/METADATA
pygeoshapes-1.0.dist-info/WHEEL
pygeoshapes-1.0.dist-info/top_level.txt
pygeoshapes-1.0.dist-info/RECORD
